{"version":1,"resource":"vscode-remote://970-cs-995b0bbd-521a-4ab1-8e7c-46e310ebfc50.cs-us-east1-vpcf.cloudshell.dev/home/leonardo_cavalcanti_136/web-service-gin/main.go","entries":[{"id":"1B2S.go","timestamp":1749471572145},{"id":"mA1V.go","timestamp":1749471827306},{"id":"UldX.go","source":"undoRedo.source","timestamp":1749471831931},{"id":"d2zw.go","timestamp":1749471851773},{"id":"VO5y.go","timestamp":1749471889641},{"id":"GTyy.go","timestamp":1749471947469},{"id":"srJX.go","timestamp":1749471990890},{"id":"V5Pr.go","timestamp":1749472095916},{"id":"5bGJ.go","timestamp":1749472174175},{"id":"fNpT.go","timestamp":1749472285423},{"id":"7JXj.go","source":"undoRedo.source","timestamp":1749472293636},{"id":"KmYx.go","timestamp":1749472294980},{"id":"IwsA.go","timestamp":1749472355057},{"id":"HAgu.go","timestamp":1749472611935},{"id":"d9sj.go","timestamp":1749472653637},{"id":"koGW.go","source":"undoRedo.source","timestamp":1749472668903},{"id":"FHqs.go","timestamp":1749472678767},{"id":"Zk4N.go","source":"undoRedo.source","timestamp":1749472681246},{"id":"8GrT.go","timestamp":1749472724489},{"id":"YuHW.go","timestamp":1749472809160},{"id":"UxlG.go","timestamp":1749472850494},{"id":"yxFV.go","timestamp":1749472879013},{"id":"jziW.go","timestamp":1749472989613},{"id":"5F7G.go","timestamp":1749473050359},{"id":"Qxwk.go","timestamp":1749473102851},{"id":"DSAA.go","timestamp":1749473220957},{"id":"h1QF.go","timestamp":1749473312563},{"id":"E2cV.go","timestamp":1749473493013},{"id":"31F5.go","timestamp":1749473511347},{"id":"Icog.go","timestamp":1749473560518},{"id":"tGlk.go","timestamp":1749473717100},{"id":"68Jw.go","timestamp":1749473876664},{"id":"ZyLK.go","timestamp":1749473908112},{"id":"jzSI.go","timestamp":1749473933085},{"id":"szKO.go","source":"undoRedo.source","timestamp":1749473947559},{"id":"2dIB.go","timestamp":1749474073294},{"id":"0P7r.go","timestamp":1749474592098},{"id":"Vl6m.go","source":"undoRedo.source","timestamp":1749474735918},{"id":"7Krk.go","timestamp":1749474758863},{"id":"Fo8r.go","source":"undoRedo.source","timestamp":1749474783269},{"id":"7Ug4.go","timestamp":1749474787660},{"id":"QxHW.go","timestamp":1749474833761},{"id":"231V.go","timestamp":1749474860951},{"id":"E4ti.go","timestamp":1749474887294},{"id":"zFYB.go","timestamp":1749475650464},{"id":"o0Rg.go","source":"undoRedo.source","timestamp":1749475660356},{"id":"Uts7.go","timestamp":1749475662964},{"id":"QzGp.go","source":"undoRedo.source","timestamp":1749475744614},{"id":"ELHE.go","timestamp":1749475856951},{"id":"MpZu.go","timestamp":1749475872582}]}